genboostgpu/__init__.py
genboostgpu/cpg_orchestration.py
genboostgpu/cpg_runner.py
genboostgpu/cpg_tuning.py
genboostgpu/data_io.py
genboostgpu/enet_boosting.py
genboostgpu/hyperparams.py
genboostgpu/orchestration.py
genboostgpu/snp_processing.py
genboostgpu/tuning.py
genboostgpu/vmr_runner.py
genboostgpu-0.3.0.dist-info/METADATA
genboostgpu-0.3.0.dist-info/WHEEL
genboostgpu-0.3.0.dist-info/RECORD
